pyhapwol/__init__.py
pyhapwol/__main__.py
pyhapwol/bridge.py
pyhapwol/network.py
pyhapwol/switch.py
pyhapwol-1.0.2.dist-info/LICENSE.txt
pyhapwol-1.0.2.dist-info/METADATA
pyhapwol-1.0.2.dist-info/WHEEL
pyhapwol-1.0.2.dist-info/entry_points.txt
pyhapwol-1.0.2.dist-info/top_level.txt
pyhapwol-1.0.2.dist-info/RECORD
