Metadata-Version: 2.1
Name: pyhapwol
Version: 1.0.2
Summary: A Wake on LAN Switch implementation for HomeKit
Home-page: https://gitlab.com/aquator/hap-wol-python
Author: István Rábel
Author-email: thraex.aquator@icloud.com
License: Unlicense
Platform: UNKNOWN
Classifier: License :: OSI Approved :: The Unlicense (Unlicense)
Classifier: Programming Language :: Python :: 3
Classifier: Programming Language :: Python :: 3.6
Classifier: Programming Language :: Python :: 3.7
Classifier: Programming Language :: Python :: 3.8
Classifier: Programming Language :: Python :: 3.9
Requires-Python: >=3.6
License-File: LICENSE.txt
Requires-Dist: click (~=8.0.0)
Requires-Dist: hap-python (~=4.1.0)
Requires-Dist: pywol (~=1.0.0)
Requires-Dist: pyyaml (~=5.4.0)
Requires-Dist: scapy (~=2.4.0)
